odoo/addons/sm_member_geolocation/__init__.py
odoo/addons/sm_member_geolocation/__manifest__.py
odoo/addons/sm_member_geolocation/models/__init__.py
odoo/addons/sm_member_geolocation/models/models_sm_geolocation_cron.py
odoo/addons/sm_member_geolocation/models/models_sm_member.py
odoo/addons/sm_member_geolocation/models/models_sm_members_zone.py
odoo/addons/sm_member_geolocation/security/ir.model.access.csv
odoo/addons/sm_member_geolocation/views/views_cron.xml
odoo/addons/sm_member_geolocation/views/views_members.xml
odoo/addons/sm_member_geolocation/views/views_members_zone.xml
odoo11_addon_sm_member_geolocation-11.0.0.0.4.dist-info/METADATA
odoo11_addon_sm_member_geolocation-11.0.0.0.4.dist-info/WHEEL
odoo11_addon_sm_member_geolocation-11.0.0.0.4.dist-info/top_level.txt
odoo11_addon_sm_member_geolocation-11.0.0.0.4.dist-info/RECORD
